MANIFEST.in
VERSION
setup.py
tensorshield.ext.wallet.egg-info/PKG-INFO
tensorshield.ext.wallet.egg-info/SOURCES.txt
tensorshield.ext.wallet.egg-info/dependency_links.txt
tensorshield.ext.wallet.egg-info/requires.txt
tensorshield.ext.wallet.egg-info/top_level.txt
tensorshield/ext/wallet/__init__.py
tensorshield/ext/wallet/package.json
tensorshield/ext/wallet/testing.py
tensorshield/ext/wallet/models/__init__.py
tensorshield/ext/wallet/models/_coldkeyref.py
tensorshield/ext/wallet/models/_hotkey.py
tensorshield/ext/wallet/models/_hotkeyprivatekey.py
tensorshield/ext/wallet/models/_hotkeypublickey.py
tensorshield/ext/wallet/models/_hotkeyref.py
tensorshield/ext/wallet/models/_hotkeyset.py